pg_import/__init__.py
pg_import/data_restore.py
pg_import/distributor.py
pg_import/executor.py
pg_import/main.py
pg_import/pg_items.py
pg_import/refresh_sequence.py
pg_import-2.6.0.dist-info/licenses/LICENSE
pg_import-2.6.0.dist-info/METADATA
pg_import-2.6.0.dist-info/WHEEL
pg_import-2.6.0.dist-info/entry_points.txt
pg_import-2.6.0.dist-info/top_level.txt
pg_import-2.6.0.dist-info/RECORD
