Metadata-Version: 2.4
Name: pg-import
Version: 2.6.0
Summary: git to pg converter
Home-page: https://github.com/comagic/pg_import
Author: Andrey Chernyakov
Author-email: a.chernyakov@comagic.dev
License: BSD
Project-URL: Documentation, https://github.com/comagic/pg_import/blob/master/README.md
Keywords: postgresql,git,ci/cd
Classifier: Development Status :: 5 - Production/Stable
Classifier: Environment :: Console
Classifier: Operating System :: OS Independent
Classifier: Programming Language :: Python :: 3.6
Classifier: Programming Language :: Python :: 3.7
Classifier: Programming Language :: Python :: 3.8
Classifier: Programming Language :: Python :: 3.9
Classifier: Programming Language :: Python :: 3.10
Requires-Python: >=3.6
License-File: LICENSE
Requires-Dist: asyncpg<0.31.0,>=0.27.0
Dynamic: author
Dynamic: author-email
Dynamic: classifier
Dynamic: description
Dynamic: home-page
Dynamic: keywords
Dynamic: license
Dynamic: license-file
Dynamic: project-url
Dynamic: requires-dist
Dynamic: requires-python
Dynamic: summary
